jax_cgd/__init__.py
jax_cgd/acgd.py
jax_cgd/cgd.py
jax_cgd/utils.py
jax_cgd/solvers/__init__.py
jax_cgd/solvers/cg.py
jax_cgd/solvers/gmres.py
jax_cgd-1.0.4.dist-info/licenses/LICENSE
jax_cgd-1.0.4.dist-info/METADATA
jax_cgd-1.0.4.dist-info/WHEEL
jax_cgd-1.0.4.dist-info/top_level.txt
jax_cgd-1.0.4.dist-info/RECORD
