Metadata-Version: 2.4
Name: jax-cgd
Version: 1.0.4
Summary: JAX implementation of Competitive Gradient Descent algorithms
Author-email: Yiming Lu <luyiming925@gmail.com>
License: MIT
Project-URL: Homepage, https://github.com/Juicy-Quadro/jax-cgd
Project-URL: Repository, https://github.com/Juicy-Quadro/jax-cgd
Project-URL: Issues, https://github.com/Juicy-Quadro/jax-cgd/issues
Keywords: jax,optimization,competitive gradient descent,machine learning
Classifier: Development Status :: 3 - Alpha
Classifier: Intended Audience :: Science/Research
Classifier: License :: OSI Approved :: MIT License
Classifier: Operating System :: OS Independent
Classifier: Programming Language :: Python :: 3.9
Classifier: Programming Language :: Python :: 3.10
Classifier: Programming Language :: Python :: 3.11
Classifier: Topic :: Scientific/Engineering :: Artificial Intelligence
Requires-Python: >=3.10
License-File: LICENSE
Requires-Dist: jax>=0.5.1
Requires-Dist: jaxlib>=0.5.1
Requires-Dist: numpy>=1.22
Requires-Dist: flax>=0.10.0
Provides-Extra: dev
Requires-Dist: pytest>=7; extra == "dev"
Requires-Dist: black>=23; extra == "dev"
Requires-Dist: flake8>=6; extra == "dev"
Requires-Dist: mypy>=1; extra == "dev"
Dynamic: license-file
